jq_by_example-0.2.1.dist-info/licenses/LICENSE
src/__init__.py
src/cli.py
src/colors.py
src/domain.py
src/executor.py
src/generator.py
src/orchestrator.py
src/providers.py
src/reviewer.py
src/security.py
jq_by_example-0.2.1.dist-info/METADATA
jq_by_example-0.2.1.dist-info/WHEEL
jq_by_example-0.2.1.dist-info/entry_points.txt
jq_by_example-0.2.1.dist-info/top_level.txt
jq_by_example-0.2.1.dist-info/RECORD
