Metadata-Version: 2.4
Name: jq-by-example
Version: 0.2.1
Summary: AI-Powered JQ Filter Synthesis Tool - synthesizes jq filters from input/output JSON examples using LLM generation with iterative refinement
Author: JQ-By-Example Contributors
License: MIT
Project-URL: Homepage, https://github.com/nulone/jq-by-example
Project-URL: Repository, https://github.com/nulone/jq-by-example
Project-URL: Issues, https://github.com/nulone/jq-by-example/issues
Keywords: jq,json,llm,synthesis,cli
Classifier: Development Status :: 3 - Alpha
Classifier: Environment :: Console
Classifier: Intended Audience :: Developers
Classifier: License :: OSI Approved :: MIT License
Classifier: Operating System :: OS Independent
Classifier: Programming Language :: Python :: 3
Classifier: Programming Language :: Python :: 3.10
Classifier: Programming Language :: Python :: 3.11
Classifier: Programming Language :: Python :: 3.12
Classifier: Topic :: Software Development :: Code Generators
Classifier: Topic :: Text Processing :: Filters
Classifier: Typing :: Typed
Requires-Python: >=3.10
License-File: LICENSE
Requires-Dist: httpx>=0.25.0
Provides-Extra: dev
Requires-Dist: pytest>=7.0; extra == "dev"
Requires-Dist: pytest-cov>=4.0; extra == "dev"
Requires-Dist: ruff>=0.14.0; extra == "dev"
Requires-Dist: mypy>=1.0; extra == "dev"
Dynamic: license-file
